bridge.py
file_reader.py
main.py
replaceapplemusic-0.0.2.dist-info/METADATA
replaceapplemusic-0.0.2.dist-info/WHEEL
replaceapplemusic-0.0.2.dist-info/entry_points.txt
replaceapplemusic-0.0.2.dist-info/top_level.txt
replaceapplemusic-0.0.2.dist-info/RECORD
