Metadata-Version: 2.1
Name: replaceapplemusic
Version: 0.0.2
Summary: A Python utility to replace source files of songs in Apple Music while preserving metadata
Home-page: https://github.com/realtvop/ReplaceAppleMusic
Author: realtvop
Classifier: Programming Language :: Python :: 3
Classifier: Operating System :: MacOS
Requires-Python: >=3.6
Requires-Dist: appscript
Requires-Dist: mutagen
